MANIFEST.in
README.rst
setup.py
Bast.egg-info/PKG-INFO
Bast.egg-info/SOURCES.txt
Bast.egg-info/dependency_links.txt
Bast.egg-info/entry_points.txt
Bast.egg-info/not-zip-safe
Bast.egg-info/requires.txt
Bast.egg-info/top_level.txt
bast/__init__.py
bast/bast.py
bast/cli.py
bast/controller.py
bast/environment.py
bast/exception.py
bast/hash.py
bast/json_.py
bast/migration.py
bast/model.py
bast/route.py
bast/session.py
bast/view.py
bast/exception/bast-logo.jpeg
bast/exception/exception.html
bast/exception/style.css
test/test.py