Metadata-Version: 1.2
Name: Bast
Version: 0.1.1.8
Summary: Simple yet Elegant Web Framework with MVC Patterns
Home-page: https://github.com/moluwole/Bast
Author: Majiyagbe Oluwole
Author-email: oluwole564@gmail.com
Maintainer: Majiyagbe Oluwole | Azeez Abiodun Solomon
License: MIT
Keywords: web framework tornado ORM MVC
Platform: any
Classifier: Development Status :: 4 - Beta
Classifier: Environment :: Web Environment
Classifier: Intended Audience :: Developers
Classifier: License :: OSI Approved :: MIT License
Classifier: Natural Language :: English
Classifier: Operating System :: OS Independent
Classifier: Programming Language :: Python :: 2
Classifier: Programming Language :: Python :: 2.7
Classifier: Programming Language :: Python :: 3
Classifier: Programming Language :: Python :: 3.4
Classifier: Programming Language :: Python :: 3.5
Classifier: Programming Language :: Python :: 3.6
Classifier: Programming Language :: Python :: 3.7
Classifier: Topic :: Internet :: WWW/HTTP :: Dynamic Content
Classifier: Topic :: Software Development :: Libraries :: Application Frameworks
Classifier: Topic :: Software Development :: Libraries :: Python Modules
